xsdata_pydantic/__init__.py
xsdata_pydantic/bindings.py
xsdata_pydantic/compat.py
xsdata_pydantic/fields.py
xsdata_pydantic/generator.py
xsdata_pydantic/py.typed
xsdata_pydantic/hooks/__init__.py
xsdata_pydantic/hooks/class_type.py
xsdata_pydantic/hooks/cli.py
xsdata_pydantic-24.5.dist-info/LICENSE
xsdata_pydantic-24.5.dist-info/METADATA
xsdata_pydantic-24.5.dist-info/WHEEL
xsdata_pydantic-24.5.dist-info/entry_points.txt
xsdata_pydantic-24.5.dist-info/top_level.txt
xsdata_pydantic-24.5.dist-info/RECORD
